winzy_wc/__init__.py
winzy_wc-0.1.dist-info/LICENSE
winzy_wc-0.1.dist-info/METADATA
winzy_wc-0.1.dist-info/WHEEL
winzy_wc-0.1.dist-info/entry_points.txt
winzy_wc-0.1.dist-info/top_level.txt
winzy_wc-0.1.dist-info/RECORD
