Metadata-Version: 2.1
Name: winzy-wc
Version: 0.1
Summary: Mimics the functionality of the 'wc' command
Author: Sukhbinder Singh
License: Apache-2.0
Project-URL: Homepage, https://github.com/sukhbinder/winzy-wc
Project-URL: Changelog, https://github.com/sukhbinder/winzy-wc/releases
Project-URL: Issues, https://github.com/sukhbinder/winzy-wc/issues
Project-URL: CI, https://github.com/sukhbinder/winzy-wc/actions
Classifier: License :: OSI Approved :: Apache Software License
License-File: LICENSE
Requires-Dist: winzy
Provides-Extra: test
Requires-Dist: pytest ; extra == 'test'
